CHANGES.txt
MANIFEST.in
README.md
setup.py
GeobricksDistribution.egg-info/PKG-INFO
GeobricksDistribution.egg-info/SOURCES.txt
GeobricksDistribution.egg-info/dependency_links.txt
GeobricksDistribution.egg-info/requires.txt
GeobricksDistribution.egg-info/top_level.txt
geobricks_distribution/__init__.py
geobricks_distribution/__init__.pyc
geobricks_distribution/config/__init__.py
geobricks_distribution/config/__init__.pyc
geobricks_distribution/config/config.py
geobricks_distribution/config/config.pyc
geobricks_distribution/config/config.py~
geobricks_distribution/core/__init__.py
geobricks_distribution/core/__init__.pyc
geobricks_distribution/core/distribution_core.py
geobricks_distribution/core/distribution_core.pyc
geobricks_distribution/rest/__init__.py
geobricks_distribution/rest/__init__.pyc
geobricks_distribution/rest/distribution_main.py
geobricks_distribution/rest/distribution_main.pyc
geobricks_distribution/rest/distribution_rest.py
geobricks_distribution/rest/distribution_rest.pyc