Metadata-Version: 1.0
Name: GeobricksDistribution
Version: 0.1.15
Summary: Geobricks geospatial data distribution library.
Home-page: http://pypi.python.org/pypi/GeobricksDistribution/
Author: Simone Murzilli; Guido Barbaglia
Author-email: geobrickspy@gmail.com
License: LICENSE.txt
Keywords: geobricks,stats,geostats,zonalstats,gis,statistics,geostatistics
Platform: UNKNOWN
